prosedecomposer/__init__.py
prosedecomposer-0.1.1.dist-info/LICENSE.md
prosedecomposer-0.1.1.dist-info/METADATA
prosedecomposer-0.1.1.dist-info/WHEEL
prosedecomposer-0.1.1.dist-info/dependency_links.txt
prosedecomposer-0.1.1.dist-info/top_level.txt
prosedecomposer-0.1.1.dist-info/zip-safe
prosedecomposer-0.1.1.dist-info/RECORD
