Metadata-Version: 2.1
Name: prosedecomposer
Version: 0.1.1
Summary: Decompose, transform, and recombine prose into mutated forms.
Home-page: https://github.com/coreybobco/prosedecomposer-py
Author: Corey Bobco
Author-email: corey.bobco@gmail.com
License: MIT
Keywords: poetry
Platform: UNKNOWN
Classifier: Development Status :: 3 - Alpha
Classifier: License :: OSI Approved :: BSD License
Classifier: Programming Language :: Python :: 3
Classifier: Programming Language :: Python :: 3.6
Classifier: Programming Language :: Python :: 3.7
Classifier: Intended Audience :: Developers
Classifier: Intended Audience :: Education
Classifier: Intended Audience :: Science/Research
Classifier: License :: OSI Approved :: MIT License
Classifier: Natural Language :: English
Classifier: Topic :: Artistic Software
Requires-Dist: Gutenberg (==0.7.0)
Requires-Dist: inflect (==2.1.0)
Requires-Dist: internetarchive (==1.8.5)
Requires-Dist: markovify (==0.7.1)
Requires-Dist: nltk (==3.4.5)
Requires-Dist: rdflib (==4.2.2)
Requires-Dist: spacy (==2.1.8)
Requires-Dist: unittest2 (==1.1.0)
Requires-Dist: wordfreq (>=2.2.1)
